streamlit_component_fill_square_cropper1/setup.py
streamlit_component_square_fill_cropper101-0.0.1.dist-info/LICENSE.txt
streamlit_component_square_fill_cropper101-0.0.1.dist-info/METADATA
streamlit_component_square_fill_cropper101-0.0.1.dist-info/WHEEL
streamlit_component_square_fill_cropper101-0.0.1.dist-info/top_level.txt
streamlit_component_square_fill_cropper101-0.0.1.dist-info/RECORD
