Metadata-Version: 2.1
Name: streamlit_component_square_fill_cropper101
Version: 0.0.1
Summary: streamlit_component_square_fill_cropper square by using color filler.
Home-page: https://github.com/webdevserv/streamlit_component_fill_square_cropper
Author: Idoia Lertxundi
Author-email: ilp <idoia@goikoa.gmail.com>
Project-URL: Homepage, https://github.com/webdevserv/streamlit_component_fill_square_cropper
Classifier: Programming Language :: Python :: 3
Classifier: License :: OSI Approved :: MIT License
Classifier: Operating System :: OS Independent
Requires-Python: >=3.6
License-File: LICENSE.txt
